{
    "raids": [
        {
            "zoneID": 1007,
            "startTime": 1640290404133,
            "reportCode": "aw7QD4bKh18GkzNd",
            "bosses": [
                "Attumen the Huntsman",
                "Maiden of Virtue",
                "Moroes",
                "Netherspite",
                "Netherspite - Wipe 1 (10.0%)",
                "Nightbane",
                "Opera Hall",
                "Prince Malchezaar",
                "Shade of Aran",
                "Terestian Illhoof",
                "The Curator"
            ]
        },
        {
            "zoneID": 1008,
            "startTime": 1640644667959,
            "reportCode": "a3y1vwWP4bNYK9RZ",
            "bosses": [
                "Gruul the Dragonkiller",
                "High King Maulgar",
                "Magtheridon"
            ]
        },
        {
            "zoneID": 1010,
            "startTime": 1641153086667,
            "reportCode": "dwJCZAWKYFDaqf1G",
            "bosses": [
                "Al'ar",
                "Fathom-Lord Karathress",
                "Fathom-Lord Karathress - Wipe 1 (96.0%)",
                "Gruul the Dragonkiller",
                "High Astromancer Solarian",
                "High King Maulgar",
                "Hydross the Unstable",
                "Kael'thas Sunstrider",
                "Kael'thas Sunstrider - Wipe 1 (60.0%)",
                "Lady Vashj",
                "Leotheras the Blind",
                "Magtheridon",
                "Morogrim Tidewalker",
                "Morogrim Tidewalker - Wipe 1 (3.0%)",
                "The Lurker Below",
                "Void Reaver"
            ]
        },
        {
            "zoneID": 1010,
            "startTime": 1642362976824,
            "reportCode": "1LZP24YGkKMyzjN8",
            "bosses": [
                "Fathom-Lord Karathress",
                "Fathom-Lord Karathress - Wipe 1 (95.0%)",
                "Hydross the Unstable",
                "Lady Vashj",
                "Leotheras the Blind",
                "Morogrim Tidewalker",
                "The Lurker Below"
            ]
        },
        {
            "zoneID": 1010,
            "startTime": 1642367379803,
            "reportCode": "cJdMtrqmgx9nFG1W",
            "bosses": [
                "Al'ar",
                "High Astromancer Solarian",
                "Kael'thas Sunstrider",
                "Void Reaver",
                "Void Reaver - Wipe 1 (94.0%)"
            ]
        },
        {
            "zoneID": 1008,
            "startTime": 1642371272640,
            "reportCode": "Hrd3RvxYFtf7a1qc",
            "bosses": [
                "Gruul the Dragonkiller",
                "High King Maulgar"
            ]
        },
        {
            "zoneID": 1008,
            "startTime": 1642372201616,
            "reportCode": "QkXFnBN7fv4hKLMq",
            "bosses": [
                "Magtheridon"
            ]
        },
        {
            "zoneID": 1010,
            "startTime": 1643227029099,
            "reportCode": "3Fv9qxpzDaYjcPwm",
            "bosses": [
                "Fathom-Lord Karathress",
                "Fathom-Lord Karathress - Wipe 1 (43.0%)",
                "Hydross the Unstable",
                "Hydross the Unstable - Wipe 1 (40.0%)",
                "Lady Vashj",
                "Leotheras the Blind",
                "Morogrim Tidewalker",
                "The Lurker Below"
            ]
        },
        {
            "zoneID": 1010,
            "startTime": 1643227572724,
            "reportCode": "MAq3gR7t8pZ4Tdxj",
            "bosses": [
                "Fathom-Lord Karathress",
                "Fathom-Lord Karathress - Wipe 1 (43.0%)",
                "Hydross the Unstable",
                "Lady Vashj",
                "Leotheras the Blind",
                "Morogrim Tidewalker",
                "The Lurker Below"
            ]
        },
        {
            "zoneID": 1010,
            "startTime": 1643232459470,
            "reportCode": "aCwA2ckTnF4LQq6d",
            "bosses": [
                "Al'ar",
                "Gruul the Dragonkiller",
                "High Astromancer Solarian",
                "High King Maulgar",
                "Kael'thas Sunstrider",
                "Void Reaver"
            ]
        },
        {
            "zoneID": 1011,
            "startTime": 1644436097141,
            "reportCode": "1mQVjY4FdL3KcDrn",
            "bosses": [
                "Anetheron",
                "Archimonde",
                "Archimonde - Wipe 1 (66.0%)",
                "Archimonde - Wipe 2 (73.0%)",
                "Archimonde - Wipe 3 (32.0%)",
                "Archimonde - Wipe 5 (0.0%)",
                "Azgalor",
                "Gurtogg Bloodboil",
                "Gurtogg Bloodboil - Wipe 1 (24.0%)",
                "Gurtogg Bloodboil - Wipe 3 (58.0%)",
                "High Warlord Naj'entus",
                "Kaz'rogal",
                "Rage Winterchill",
                "Reliquary of Souls",
                "Shade of Akama",
                "Supremus",
                "Teron Gorefiend",
                "Trash 1 - Ghoul",
                "Trash 10 - Ghoul",
                "Trash 11 - Ghoul",
                "Trash 12 - Ghoul",
                "Trash 13 - Banshee",
                "Trash 14 - Banshee",
                "Trash 15 - Ghoul",
                "Trash 16 - Banshee",
                "Trash 17 - Banshee",
                "Trash 19 - Banshee",
                "Trash 2 - Ghoul",
                "Trash 20 - Gargoyle",
                "Trash 21 - Ghoul",
                "Trash 22 - Gargoyle",
                "Trash 23 - Ghoul",
                "Trash 24 - Gargoyle",
                "Trash 25 - Frost Wyrm",
                "Trash 26 - Banshee",
                "Trash 27 - Abomination",
                "Trash 28 - Gargoyle",
                "Trash 29 - Giant Infernal",
                "Trash 3 - Ghoul",
                "Trash 30 - Giant Infernal",
                "Trash 31 - Abomination",
                "Trash 32 - Banshee",
                "Trash 33 - Giant Infernal",
                "Trash 34 - Banshee",
                "Trash 35 - Unknown",
                "Trash 36 - Aqueous Spawn",
                "Trash 37 - Leviathan",
                "Trash 38 - Coilskar Wrangler",
                "Trash 39 - Aqueous Spawn",
                "Trash 4 - Ghoul",
                "Trash 40 - Leviathan",
                "Trash 41 - Dragon Turtle",
                "Trash 42 - Coilskar Wrangler",
                "Trash 43 - Aqueous Spawn",
                "Trash 44 - Aqueous Spawn",
                "Trash 45 - Aqueous Spawn",
                "Trash 46 - Bonechewer Worker",
                "Trash 47 - Dragonmaw Wyrmcaller",
                "Trash 48 - Bonechewer Worker",
                "Trash 49 - Illidari Defiler",
                "Trash 5 - Ghoul",
                "Trash 50 - Illidari Boneslicer",
                "Trash 51 - Ashtongue Feral Spirit",
                "Trash 52 - High Nethermancer Zerevor",
                "Trash 53 - Ashtongue Feral Spirit",
                "Trash 54 - Ashtongue Stalker",
                "Trash 55 - Bonechewer Brawler",
                "Trash 56 - Bonechewer Brawler",
                "Trash 57 - Bonechewer Brawler",
                "Trash 58 - High Nethermancer Zerevor",
                "Trash 59 - High Nethermancer Zerevor",
                "Trash 6 - Ghoul",
                "Trash 60 - Shadowmoon Champion",
                "Trash 61 - Shadowmoon Deathshaper",
                "Trash 62 - Shadowmoon Grunt",
                "Trash 63 - High Nethermancer Zerevor",
                "Trash 64 - Hand of Gorefiend",
                "Trash 65 - Hand of Gorefiend",
                "Trash 66 - High Nethermancer Zerevor",
                "Trash 67 - Mutant War Hound",
                "Trash 68 - Bonechewer Brawler",
                "Trash 69 - Bonechewer Blade Fury",
                "Trash 7 - Ghoul",
                "Trash 70 - Angered Soul Fragment",
                "Trash 71 - Suffering Soul Fragment",
                "Trash 72 - Bonechewer Brawler",
                "Trash 73 - High Nethermancer Zerevor",
                "Trash 74 - Gurtogg Fi\u00e8vresang",
                "Trash 8 - Ghoul",
                "Trash 9 - Rage Froidhiver"
            ]
        },
        {
            "zoneID": 1011,
            "startTime": 1644522194760,
            "reportCode": "KQh8kN9AVpyfCwTB",
            "bosses": [
                "Illidan Stormrage",
                "Mother Shahraz",
                "The Illidari Council",
                "The Illidari Council - Wipe 1 (96.2%)",
                "Trash 1 - Charming Courtesan",
                "Trash 10 - Promenade Sentinel",
                "Trash 11 - Promenade Sentinel",
                "Trash 12 - High Nethermancer Zerevor",
                "Trash 13 - Illidari Blood Lord",
                "Trash 14 - Illidari Blood Lord",
                "Trash 2 - Sister of Pleasure",
                "Trash 3 - High Nethermancer Zerevor",
                "Trash 4 - Enslaved Servant",
                "Trash 5 - Sister of Pleasure",
                "Trash 6 - Sister of Pleasure",
                "Trash 7 - Toad",
                "Trash 8 - High Nethermancer Zerevor",
                "Trash 9 - Promenade Sentinel"
            ]
        },
        {
            "zoneID": 1011,
            "startTime": 1645387213207,
            "reportCode": "2g6MdG8CcKmVJ7ta",
            "bosses": [
                "Gurtogg Bloodboil",
                "High Warlord Naj'entus",
                "Illidan Stormrage",
                "Mother Shahraz",
                "Reliquary of Souls",
                "Shade of Akama",
                "Supremus",
                "Teron Gorefiend",
                "The Illidari Council",
                "Trash 1 - Aqueous Spawn",
                "Trash 10 - Bonechewer Worker",
                "Trash 11 - Dragonmaw Wind Reaver",
                "Trash 12 - Illidari Defiler",
                "Trash 13 - High Nethermancer Zerevor",
                "Trash 14 - Storm Fury",
                "Trash 15 - Illidari Defiler",
                "Trash 16 - Ashtongue Battlelord",
                "Trash 17 - High Nethermancer Zerevor",
                "Trash 18 - Bonechewer Combatant",
                "Trash 19 - Ashtongue Battlelord",
                "Trash 2 - Aqueous Spawn",
                "Trash 20 - Ashtongue Stalker",
                "Trash 21 - High Nethermancer Zerevor",
                "Trash 22 - Shadowmoon Houndmaster",
                "Trash 23 - High Nethermancer Zerevor",
                "Trash 24 - Shadowmoon Champion",
                "Trash 25 - Shadowmoon Blood Mage",
                "Trash 26 - Hand of Gorefiend",
                "Trash 27 - Bonechewer Brawler",
                "Trash 28 - Mutant War Hound",
                "Trash 29 - Bonechewer Behemoth",
                "Trash 3 - Leviathan",
                "Trash 30 - Bonechewer Brawler",
                "Trash 31 - High Nethermancer Zerevor",
                "Trash 32 - Bonechewer Brawler",
                "Trash 33 - Suffering Soul Fragment",
                "Trash 34 - Bonechewer Brawler",
                "Trash 35 - High Nethermancer Zerevor",
                "Trash 36 - Bonechewer Brawler",
                "Trash 37 - Illidari Defiler",
                "Trash 38 - High Nethermancer Zerevor",
                "Trash 39 - Sister of Pleasure",
                "Trash 4 - Aqueous Surger",
                "Trash 40 - Temple Concubine",
                "Trash 41 - High Nethermancer Zerevor",
                "Trash 42 - Promenade Sentinel",
                "Trash 43 - Promenade Sentinel",
                "Trash 44 - High Nethermancer Zerevor",
                "Trash 45 - Illidari Blood Lord",
                "Trash 46 - Illidari Blood Lord",
                "Trash 5 - Aqueous Spawn",
                "Trash 6 - Aqueous Spawn",
                "Trash 7 - Dragonmaw Wyrmcaller",
                "Trash 8 - Dragonmaw Wind Reaver",
                "Trash 9 - Illidari Fearbringer"
            ]
        },
        {
            "zoneID": 1011,
            "startTime": 1645476821658,
            "reportCode": "RBCmakKxjVMzgH2y",
            "bosses": [
                "Anetheron",
                "Archimonde",
                "Archimonde - Wipe 2 (0.0%)",
                "Azgalor",
                "Kaz'rogal",
                "Rage Winterchill",
                "Trash 1 - Ghoul",
                "Trash 10 - Ghoul",
                "Trash 11 - Banshee",
                "Trash 12 - Banshee",
                "Trash 13 - Ghoul",
                "Trash 14 - Banshee",
                "Trash 15 - Abomination",
                "Trash 16 - Banshee",
                "Trash 17 - Ghoul",
                "Trash 18 - Gargoyle",
                "Trash 19 - Ghoul",
                "Trash 2 - Ghoul",
                "Trash 20 - Gargoyle",
                "Trash 21 - Ghoul",
                "Trash 22 - Gargoyle",
                "Trash 23 - Frost Wyrm",
                "Trash 24 - Ghoul",
                "Trash 25 - Abomination",
                "Trash 26 - Gargoyle",
                "Trash 27 - Giant Infernal",
                "Trash 28 - Giant Infernal",
                "Trash 29 - Abomination",
                "Trash 3 - Ghoul",
                "Trash 30 - Banshee",
                "Trash 31 - Giant Infernal",
                "Trash 32 - Banshee",
                "Trash 4 - Ghoul",
                "Trash 5 - Ghoul",
                "Trash 6 - Ghoul",
                "Trash 7 - Ghoul",
                "Trash 8 - Ghoul",
                "Trash 9 - Ghoul"
            ]
        },
        {
            "zoneID": 1011,
            "startTime": 1645646400611,
            "reportCode": "wmgaQvhGW1fqZ7dy",
            "bosses": [
                "Anetheron",
                "Rage Winterchill",
                "Trash 1 - Ghoul",
                "Trash 10 - Ghoul",
                "Trash 11 - Ghoul",
                "Trash 12 - Banshee",
                "Trash 13 - Banshee",
                "Trash 14 - Ghoul",
                "Trash 15 - Banshee",
                "Trash 16 - Banshee",
                "Trash 17 - Banshee",
                "Trash 18 - Gargoyle",
                "Trash 19 - Ghoul",
                "Trash 2 - Ghoul",
                "Trash 20 - Gargoyle",
                "Trash 21 - Ghoul",
                "Trash 22 - Gargoyle",
                "Trash 23 - Frost Wyrm",
                "Trash 3 - Ghoul",
                "Trash 4 - Ghoul",
                "Trash 5 - Ghoul",
                "Trash 6 - Ghoul",
                "Trash 7 - Ghoul",
                "Trash 8 - Ghoul",
                "Trash 9 - Ghoul"
            ]
        },
        {
            "zoneID": 1011,
            "startTime": 1645646711305,
            "reportCode": "R38Zbr7BCAVxyFTh",
            "bosses": [
                "Anetheron",
                "Archimonde",
                "Archimonde - Wipe 2 (0.0%)",
                "Azgalor",
                "Kaz'rogal",
                "Rage Winterchill",
                "Trash 1 - Ghoul",
                "Trash 10 - Ghoul",
                "Trash 11 - Ghoul",
                "Trash 12 - Banshee",
                "Trash 13 - Banshee",
                "Trash 14 - Ghoul",
                "Trash 15 - Ghoul",
                "Trash 16 - Banshee",
                "Trash 17 - Banshee",
                "Trash 18 - Gargoyle",
                "Trash 19 - Ghoul",
                "Trash 2 - Ghoul",
                "Trash 20 - Gargoyle",
                "Trash 21 - Ghoul",
                "Trash 22 - Gargoyle",
                "Trash 23 - Frost Wyrm",
                "Trash 24 - Banshee",
                "Trash 25 - Abomination",
                "Trash 26 - Gargoyle",
                "Trash 27 - Giant Infernal",
                "Trash 28 - Giant Infernal",
                "Trash 29 - Abomination",
                "Trash 3 - Ghoul",
                "Trash 30 - Banshee",
                "Trash 31 - Giant Infernal",
                "Trash 32 - Banshee",
                "Trash 4 - Ghoul",
                "Trash 5 - Ghoul",
                "Trash 6 - Ghoul",
                "Trash 7 - Ghoul",
                "Trash 8 - Ghoul",
                "Trash 9 - Ghoul"
            ]
        },
        {
            "zoneID": 1011,
            "startTime": 1645732042009,
            "reportCode": "p8g1A9RGmvM4bnQw",
            "bosses": [
                "Gurtogg Bloodboil",
                "High Warlord Naj'entus",
                "Illidan Stormrage",
                "Mother Shahraz",
                "Reliquary of Souls",
                "Reliquary of Souls - Wipe 1 (9.9%)",
                "Reliquary of Souls - Wipe 2 (33.0%)",
                "Shade of Akama",
                "Supremus",
                "Teron Gorefiend",
                "The Illidari Council",
                "The Illidari Council - Wipe 1 (97.2%)",
                "The Illidari Council - Wipe 2 (78.5%)",
                "Trash 1 - Coilskar Wrangler",
                "Trash 10 - Illidari Fearbringer",
                "Trash 11 - Dragonmaw Wyrmcaller",
                "Trash 12 - Illidari Fearbringer",
                "Trash 13 - Illidari Fearbringer",
                "Trash 14 - Shadowmoon Deathshaper",
                "Trash 15 - Illidari Boneslicer",
                "Trash 16 - Storm Fury",
                "Trash 17 - High Nethermancer Zerevor",
                "Trash 18 - Ashtongue Feral Spirit",
                "Trash 19 - Bonechewer Combatant",
                "Trash 2 - Aqueous Spawn",
                "Trash 20 - Bonechewer Brawler",
                "Trash 21 - Shadowmoon Champion",
                "Trash 22 - Shadowmoon Champion",
                "Trash 23 - High Nethermancer Zerevor",
                "Trash 24 - Shadowmoon Soldier",
                "Trash 25 - Shadowmoon Champion",
                "Trash 26 - Shadowmoon Houndmaster",
                "Trash 27 - Shadowmoon Grunt",
                "Trash 28 - High Nethermancer Zerevor",
                "Trash 29 - Hand of Gorefiend",
                "Trash 3 - Leviathan",
                "Trash 30 - Hand of Gorefiend",
                "Trash 31 - Bonechewer Brawler",
                "Trash 32 - High Nethermancer Zerevor",
                "Trash 33 - Bonechewer Brawler",
                "Trash 34 - Mutant War Hound",
                "Trash 35 - High Nethermancer Zerevor",
                "Trash 36 - Bonechewer Blade Fury",
                "Trash 37 - Angered Soul Fragment",
                "Trash 38 - Suffering Soul Fragment",
                "Trash 39 - Hungering Soul Fragment",
                "Trash 4 - Aqueous Surger",
                "Trash 41 - Illidari Boneslicer",
                "Trash 42 - Sister of Pleasure",
                "Trash 43 - Sister of Pleasure",
                "Trash 44 - Keva",
                "Trash 45 - High Nethermancer Zerevor",
                "Trash 46 - Charming Courtesan",
                "Trash 47 - Priestess of Delight",
                "Trash 48 - Promenade Sentinel",
                "Trash 49 - High Nethermancer Zerevor",
                "Trash 5 - Aqueous Spawn",
                "Trash 50 - Promenade Sentinel",
                "Trash 51 - Illidari Blood Lord",
                "Trash 52 - Illidari Blood Lord",
                "Trash 53 - Le conseil illidari",
                "Trash 6 - Coilskar Wrangler",
                "Trash 7 - Aqueous Spawn",
                "Trash 8 - Coilskar Wrangler",
                "Trash 9 - Dragonmaw Wyrmcaller"
            ]
        },
        {
            "zoneID": 1011,
            "startTime": 1645732343679,
            "reportCode": "FDrpWLKX2CPxm613",
            "bosses": [
                "Gurtogg Bloodboil",
                "High Warlord Naj'entus",
                "Illidan Stormrage",
                "Mother Shahraz",
                "Reliquary of Souls",
                "Reliquary of Souls - Wipe 1 (19.5%)",
                "Reliquary of Souls - Wipe 2 (20.5%)",
                "Shade of Akama",
                "Supremus",
                "Teron Gorefiend",
                "The Illidari Council",
                "The Illidari Council - Wipe 1 (97.2%)",
                "The Illidari Council - Wipe 2 (78.5%)",
                "Trash 1 - Aqueous Spawn",
                "Trash 10 - Illidari Fearbringer",
                "Trash 11 - Dragonmaw Wyrmcaller",
                "Trash 12 - Illidari Fearbringer",
                "Trash 13 - Illidari Fearbringer",
                "Trash 14 - Shadowmoon Deathshaper",
                "Trash 15 - Illidari Boneslicer",
                "Trash 16 - Storm Fury",
                "Trash 17 - Illidari Defiler",
                "Trash 18 - Ashtongue Feral Spirit",
                "Trash 19 - Bonechewer Combatant",
                "Trash 2 - Aqueous Spawn",
                "Trash 20 - Ashtongue Battlelord",
                "Trash 21 - Shadowmoon Champion",
                "Trash 22 - Shadowmoon Champion",
                "Trash 23 - High Nethermancer Zerevor",
                "Trash 24 - Shadowmoon Soldier",
                "Trash 25 - Shadowmoon Champion",
                "Trash 26 - Shadowmoon Houndmaster",
                "Trash 28 - High Nethermancer Zerevor",
                "Trash 29 - Hand of Gorefiend",
                "Trash 3 - Leviathan",
                "Trash 30 - Hand of Gorefiend",
                "Trash 31 - Bonechewer Brawler",
                "Trash 32 - High Nethermancer Zerevor",
                "Trash 33 - Bonechewer Brawler",
                "Trash 34 - Mutant War Hound",
                "Trash 35 - High Nethermancer Zerevor",
                "Trash 36 - Bonechewer Blade Fury",
                "Trash 37 - Angered Soul Fragment",
                "Trash 38 - Suffering Soul Fragment",
                "Trash 39 - Hungering Soul Fragment",
                "Trash 4 - Aqueous Surger",
                "Trash 41 - Illidari Boneslicer",
                "Trash 42 - Sister of Pleasure",
                "Trash 43 - Sister of Pleasure",
                "Trash 44 - Keva",
                "Trash 45 - High Nethermancer Zerevor",
                "Trash 46 - Charming Courtesan",
                "Trash 47 - Priestess of Delight",
                "Trash 48 - Promenade Sentinel",
                "Trash 49 - High Nethermancer Zerevor",
                "Trash 5 - Aqueous Spawn",
                "Trash 50 - Promenade Sentinel",
                "Trash 51 - Illidari Blood Lord",
                "Trash 52 - Illidari Blood Lord",
                "Trash 53 - Le conseil illidari",
                "Trash 6 - Coilskar Wrangler",
                "Trash 7 - Aqueous Spawn",
                "Trash 9 - Dragonmaw Wyrmcaller"
            ]
        }
    ],
    "attendance": {
        "kharazan": {
            "percentage": 0.02564102564102564,
            "details": {
                "2021-12-22": [
                    "aw7QD4bKh18GkzNd"
                ]
            }
        },
        "gruul": {
            "percentage": 0.10256410256410256,
            "details": {
                "2021-12-22": [
                    "a3y1vwWP4bNYK9RZ"
                ],
                "2021-12-29": [
                    "dwJCZAWKYFDaqf1G"
                ],
                "2022-01-12": [
                    "Hrd3RvxYFtf7a1qc"
                ],
                "2022-01-26": [
                    "aCwA2ckTnF4LQq6d"
                ]
            }
        },
        "magtheridon": {
            "percentage": 0.07692307692307693,
            "details": {
                "2021-12-22": [
                    "a3y1vwWP4bNYK9RZ"
                ],
                "2021-12-29": [
                    "dwJCZAWKYFDaqf1G"
                ],
                "2022-01-12": [
                    "QkXFnBN7fv4hKLMq"
                ]
            }
        },
        "ssc": {
            "percentage": 0.125,
            "details": {
                "2021-12-29": [
                    "dwJCZAWKYFDaqf1G"
                ],
                "2022-01-12": [
                    "1LZP24YGkKMyzjN8"
                ],
                "2022-01-26": [
                    "3Fv9qxpzDaYjcPwm",
                    "MAq3gR7t8pZ4Tdxj"
                ]
            }
        },
        "tk": {
            "percentage": 0.125,
            "details": {
                "2021-12-29": [
                    "dwJCZAWKYFDaqf1G"
                ],
                "2022-01-12": [
                    "cJdMtrqmgx9nFG1W"
                ],
                "2022-01-26": [
                    "aCwA2ckTnF4LQq6d"
                ]
            }
        },
        "hyjal": {
            "percentage": 0.75,
            "details": {
                "2022-02-09": [
                    "1mQVjY4FdL3KcDrn"
                ],
                "2022-02-16": [
                    "RBCmakKxjVMzgH2y"
                ],
                "2022-02-23": [
                    "wmgaQvhGW1fqZ7dy",
                    "R38Zbr7BCAVxyFTh"
                ]
            }
        },
        "bt": {
            "percentage": 0.75,
            "details": {
                "2022-02-09": [
                    "1mQVjY4FdL3KcDrn",
                    "KQh8kN9AVpyfCwTB"
                ],
                "2022-02-16": [
                    "2g6MdG8CcKmVJ7ta"
                ],
                "2022-02-23": [
                    "p8g1A9RGmvM4bnQw",
                    "FDrpWLKX2CPxm613"
                ]
            }
        }
    },
    "name": "B\u00e3by"
}