{
    "raids": [
        {
            "zoneID": 1008,
            "startTime": 1637615182783,
            "reportCode": "w2agVr4pWPALZnRq",
            "bosses": [
                "High King Maulgar"
            ]
        },
        {
            "zoneID": 1008,
            "startTime": 1637615182783,
            "reportCode": "hLwq4tAz8bPj2QXW",
            "bosses": [
                "Gruul the Dragonkiller",
                "High King Maulgar",
                "Magtheridon",
                "Magtheridon - Wipe 1 (61.0%)"
            ]
        }
    ],
    "attendance": {
        "kharazan": {
            "percentage": 0.0,
            "details": {}
        },
        "gruul": {
            "percentage": 0.038461538461538464,
            "details": {
                "2021-11-17": [
                    "w2agVr4pWPALZnRq",
                    "hLwq4tAz8bPj2QXW"
                ]
            }
        },
        "magtheridon": {
            "percentage": 0.038461538461538464,
            "details": {
                "2021-11-17": [
                    "hLwq4tAz8bPj2QXW"
                ]
            }
        },
        "ssc": {
            "percentage": 0.0,
            "details": {}
        },
        "tk": {
            "percentage": 0.0,
            "details": {}
        }
    },
    "name": "Crutia"
}