{
    "raids": [
        {
            "zoneID": 1007,
            "startTime": 1629745830577,
            "reportCode": "H79LaAw2TM4WKtGj",
            "bosses": [
                "Attumen the Huntsman",
                "Moroes",
                "Maiden of Virtue - Wipe 1 (37%)",
                "Maiden of Virtue",
                "Opera Hall",
                "The Curator",
                "Terestian Illhoof",
                "Shade of Aran",
                "Netherspite - Wipe 1 (31%)",
                "Netherspite",
                "Prince Malchezaar"
            ]
        },
        {
            "zoneID": 1007,
            "startTime": 1630004423436,
            "reportCode": "DwJ1BxHb6vTtRr7q",
            "bosses": [
                "Attumen the Huntsman",
                "Moroes",
                "Maiden of Virtue",
                "Opera Hall",
                "Nightbane",
                "The Curator",
                "Terestian Illhoof",
                "Shade of Aran - Wipe 1 (9%)",
                "Shade of Aran - Wipe 2 (22%)",
                "Shade of Aran",
                "Netherspite",
                "Prince Malchezaar"
            ]
        },
        {
            "zoneID": 1008,
            "startTime": 1630263328010,
            "reportCode": "Y8vQWd2mHLrhyD4k",
            "bosses": [
                "High King Maulgar - Wipe 1 (68.99%)",
                "High King Maulgar",
                "Gruul the Dragonkiller - Wipe 1 (16%)",
                "Gruul the Dragonkiller",
                "Magtheridon - Wipe 1 (43%)",
                "Magtheridon - Wipe 2 (100%)"
            ]
        },
        {
            "zoneID": 1007,
            "startTime": 1631478012967,
            "reportCode": "1FAg938n7dc4hmkY",
            "bosses": [
                "Attumen the Huntsman",
                "Moroes",
                "Maiden of Virtue",
                "Opera Hall",
                "Nightbane",
                "The Curator",
                "Terestian Illhoof",
                "Shade of Aran",
                "Netherspite",
                "Prince Malchezaar"
            ]
        },
        {
            "zoneID": 1008,
            "startTime": 1631735917879,
            "reportCode": "AwzDtkJpV16dYmNv",
            "bosses": [
                "High King Maulgar",
                "Gruul the Dragonkiller",
                "Magtheridon"
            ]
        },
        {
            "zoneID": 1008,
            "startTime": 1632769152670,
            "reportCode": "aqYkFCgDRKBLZ4rJ",
            "bosses": [
                "High King Maulgar",
                "Gruul the Dragonkiller"
            ]
        },
        {
            "zoneID": 1008,
            "startTime": 1632770929313,
            "reportCode": "JdVhRBNmn8a7Cwkq",
            "bosses": [
                "Magtheridon"
            ]
        }
    ],
    "attendance": {
        "kharazan": {
            "percentage": 0.17647058823529413,
            "details": {
                "2021-08-18": [
                    "H79LaAw2TM4WKtGj"
                ],
                "2021-08-25": [
                    "DwJ1BxHb6vTtRr7q"
                ],
                "2021-09-08": [
                    "1FAg938n7dc4hmkY"
                ]
            }
        },
        "gruul": {
            "percentage": 0.17647058823529413,
            "details": {
                "2021-08-25": [
                    "Y8vQWd2mHLrhyD4k"
                ],
                "2021-09-15": [
                    "AwzDtkJpV16dYmNv"
                ],
                "2021-09-22": [
                    "aqYkFCgDRKBLZ4rJ"
                ]
            }
        },
        "magtheridon": {
            "percentage": 0.11764705882352941,
            "details": {
                "2021-09-15": [
                    "AwzDtkJpV16dYmNv"
                ],
                "2021-09-22": [
                    "JdVhRBNmn8a7Cwkq"
                ]
            }
        },
        "ssc": {
            "percentage": 0.0,
            "details": {}
        },
        "tk": {
            "percentage": 0.0,
            "details": {}
        }
    },
    "name": "Mamoth"
}