{
    "raids": [
        {
            "zoneID": 1007,
            "startTime": 1630350609637,
            "reportCode": "AP9VBgb76dTW3Fxj",
            "bosses": [
                "Attumen the Huntsman",
                "Maiden of Virtue",
                "Maiden of Virtue - Wipe 1 (22%)",
                "Moroes",
                "Netherspite",
                "Opera Hall",
                "Prince Malchezaar",
                "Shade of Aran",
                "Terestian Illhoof",
                "The Curator"
            ]
        },
        {
            "zoneID": 1007,
            "startTime": 1630609674422,
            "reportCode": "mg7WhzNG2dDFp6VQ",
            "bosses": [
                "Attumen the Huntsman",
                "Maiden of Virtue",
                "Moroes",
                "Netherspite",
                "Nightbane",
                "Opera Hall",
                "Prince Malchezaar",
                "Shade of Aran",
                "Shade of Aran - Wipe 1 (5%)",
                "Terestian Illhoof",
                "The Curator"
            ]
        },
        {
            "zoneID": 1007,
            "startTime": 1631214940771,
            "reportCode": "q2VktcwAp8yP1QvB",
            "bosses": [
                "Attumen the Huntsman",
                "Maiden of Virtue",
                "Moroes",
                "Netherspite",
                "Nightbane",
                "Opera Hall",
                "Prince Malchezaar",
                "Shade of Aran",
                "Terestian Illhoof",
                "The Curator"
            ]
        },
        {
            "zoneID": 1007,
            "startTime": 1632575895092,
            "reportCode": "DbAhQYFaL26xj39N",
            "bosses": [
                "Attumen the Huntsman",
                "Maiden of Virtue",
                "Moroes",
                "Moroes - Wipe 1 (88.2%)",
                "Netherspite",
                "Nightbane",
                "Opera Hall",
                "Prince Malchezaar",
                "Shade of Aran",
                "Terestian Illhoof",
                "The Curator"
            ]
        },
        {
            "zoneID": 1008,
            "startTime": 1632769152670,
            "reportCode": "aqYkFCgDRKBLZ4rJ",
            "bosses": [
                "Gruul the Dragonkiller",
                "High King Maulgar"
            ]
        },
        {
            "zoneID": 1008,
            "startTime": 1632770929313,
            "reportCode": "JdVhRBNmn8a7Cwkq",
            "bosses": [
                "Magtheridon"
            ]
        },
        {
            "zoneID": 1007,
            "startTime": 1633116114661,
            "reportCode": "rnjZqJNwcXF8CY6Q",
            "bosses": [
                "Attumen the Huntsman",
                "Maiden of Virtue",
                "Moroes",
                "Netherspite",
                "Nightbane",
                "Opera Hall",
                "Prince Malchezaar",
                "Shade of Aran",
                "Terestian Illhoof",
                "The Curator"
            ]
        },
        {
            "zoneID": 1007,
            "startTime": 1633116231380,
            "reportCode": "6P7hW1vajLwnkfrJ",
            "bosses": [
                "Attumen the Huntsman",
                "Maiden of Virtue",
                "Moroes",
                "Netherspite",
                "Nightbane",
                "Opera Hall",
                "Prince Malchezaar",
                "Shade of Aran",
                "Terestian Illhoof",
                "The Curator"
            ]
        },
        {
            "zoneID": 1007,
            "startTime": 1633720668190,
            "reportCode": "3NWZ9pcKAbYPfqxC",
            "bosses": [
                "Attumen the Huntsman",
                "Maiden of Virtue",
                "Moroes",
                "Netherspite",
                "Nightbane",
                "Opera Hall",
                "Prince Malchezaar",
                "Shade of Aran",
                "Terestian Illhoof",
                "The Curator"
            ]
        },
        {
            "zoneID": 1007,
            "startTime": 1634389716936,
            "reportCode": "92tJC1P8zdqrZ43p",
            "bosses": [
                "Attumen the Huntsman",
                "Maiden of Virtue",
                "Moroes",
                "Netherspite",
                "Nightbane",
                "Opera Hall",
                "Prince Malchezaar",
                "Shade of Aran",
                "Terestian Illhoof",
                "The Curator"
            ]
        },
        {
            "zoneID": 1007,
            "startTime": 1634930587894,
            "reportCode": "gJYCFPmqfZVbRNhn",
            "bosses": [
                "Attumen the Huntsman",
                "Maiden of Virtue",
                "Moroes",
                "Netherspite",
                "Nightbane",
                "Opera Hall",
                "Prince Malchezaar",
                "Shade of Aran",
                "Terestian Illhoof",
                "The Curator"
            ]
        },
        {
            "zoneID": 1008,
            "startTime": 1635457617168,
            "reportCode": "zbJPGpZVCYyrhH1T",
            "bosses": [
                "Gruul the Dragonkiller",
                "High King Maulgar",
                "High King Maulgar - Wipe 1 (62%)",
                "Magtheridon"
            ]
        },
        {
            "zoneID": 1007,
            "startTime": 1635798589607,
            "reportCode": "wpNmcMPzRyYq2Jbr",
            "bosses": [
                "Attumen the Huntsman",
                "Maiden of Virtue",
                "Moroes",
                "Netherspite",
                "Nightbane",
                "Opera Hall",
                "Prince Malchezaar - Wipe 1 (35%)",
                "Shade of Aran",
                "Terestian Illhoof",
                "The Curator"
            ]
        },
        {
            "zoneID": 1007,
            "startTime": 1635805442184,
            "reportCode": "pGKVvA7NamrH9bzY",
            "bosses": [
                "Prince Malchezaar"
            ]
        },
        {
            "zoneID": 1007,
            "startTime": 1635970345902,
            "reportCode": "rQNpkmzwYctVnWF9",
            "bosses": [
                "Attumen the Huntsman",
                "Maiden of Virtue",
                "Moroes",
                "Netherspite",
                "Nightbane",
                "Opera Hall",
                "Prince Malchezaar",
                "Shade of Aran",
                "Terestian Illhoof",
                "The Curator"
            ]
        },
        {
            "zoneID": 1008,
            "startTime": 1636055669700,
            "reportCode": "vNkLFVZ6mHTPt7G1",
            "bosses": [
                "High King Maulgar"
            ]
        },
        {
            "zoneID": 1008,
            "startTime": 1636056446318,
            "reportCode": "cW62MmnpTJ98bzPL",
            "bosses": [
                "Gruul the Dragonkiller",
                "Magtheridon",
                "Magtheridon - Wipe 1 (71%)"
            ]
        },
        {
            "zoneID": 1008,
            "startTime": 1637013009524,
            "reportCode": "7RnchN3rf4Zw6Pbm",
            "bosses": [
                "Magtheridon"
            ]
        },
        {
            "zoneID": 1008,
            "startTime": 1637266996188,
            "reportCode": "qwJgkXp6FyPv8bcx",
            "bosses": [
                "Gruul the Dragonkiller",
                "High King Maulgar",
                "Magtheridon",
                "Magtheridon - Wipe 1 (96.0%)"
            ]
        },
        {
            "zoneID": 1007,
            "startTime": 1637270381359,
            "reportCode": "Wfx2czGhb497nwjC",
            "bosses": [
                "Attumen the Huntsman",
                "Maiden of Virtue",
                "Moroes",
                "Netherspite",
                "Nightbane",
                "Opera Hall",
                "Prince Malchezaar",
                "Shade of Aran",
                "Terestian Illhoof",
                "The Curator"
            ]
        },
        {
            "zoneID": 1010,
            "startTime": 1638215543068,
            "reportCode": "jK9WdpQRxD32MP7b",
            "bosses": [
                "Gruul the Dragonkiller",
                "High King Maulgar",
                "Magtheridon"
            ]
        },
        {
            "zoneID": 1008,
            "startTime": 1638475404041,
            "reportCode": "gtJAxkMbh7m2RrBT",
            "bosses": [
                "Attumen the Huntsman",
                "Maiden of Virtue",
                "Moroes",
                "Netherspite",
                "Nightbane",
                "Opera Hall",
                "Prince Malchezaar",
                "Shade of Aran",
                "Terestian Illhoof",
                "The Curator"
            ]
        },
        {
            "zoneID": 1007,
            "startTime": 1639083158722,
            "reportCode": "nhKArdJgLzmwtHbD",
            "bosses": [
                "Attumen the Huntsman",
                "Maiden of Virtue",
                "Moroes",
                "Netherspite",
                "Nightbane",
                "Opera Hall",
                "Prince Malchezaar",
                "Shade of Aran",
                "Terestian Illhoof",
                "The Curator"
            ]
        },
        {
            "zoneID": 1007,
            "startTime": 1639685664173,
            "reportCode": "x1qNrKwgcW4mMGn3",
            "bosses": [
                "Attumen the Huntsman",
                "Maiden of Virtue",
                "Moroes",
                "Netherspite",
                "Nightbane",
                "Opera Hall",
                "Prince Malchezaar",
                "Shade of Aran",
                "Terestian Illhoof",
                "The Curator",
                "The Curator - Wipe 1 (92.0%)"
            ]
        }
    ],
    "attendance": {
        "kharazan": {
            "percentage": 0.4827586206896552,
            "details": {
                "2021-08-25": [
                    "AP9VBgb76dTW3Fxj"
                ],
                "2021-09-01": [
                    "mg7WhzNG2dDFp6VQ"
                ],
                "2021-09-08": [
                    "q2VktcwAp8yP1QvB"
                ],
                "2021-09-22": [
                    "DbAhQYFaL26xj39N"
                ],
                "2021-09-29": [
                    "rnjZqJNwcXF8CY6Q",
                    "6P7hW1vajLwnkfrJ"
                ],
                "2021-10-06": [
                    "3NWZ9pcKAbYPfqxC"
                ],
                "2021-10-13": [
                    "92tJC1P8zdqrZ43p"
                ],
                "2021-10-20": [
                    "gJYCFPmqfZVbRNhn"
                ],
                "2021-10-27": [
                    "wpNmcMPzRyYq2Jbr",
                    "pGKVvA7NamrH9bzY"
                ],
                "2021-11-03": [
                    "rQNpkmzwYctVnWF9"
                ],
                "2021-11-17": [
                    "Wfx2czGhb497nwjC"
                ],
                "2021-12-01": [
                    "gtJAxkMbh7m2RrBT"
                ],
                "2021-12-08": [
                    "nhKArdJgLzmwtHbD"
                ],
                "2021-12-15": [
                    "x1qNrKwgcW4mMGn3"
                ]
            }
        },
        "gruul": {
            "percentage": 0.1724137931034483,
            "details": {
                "2021-09-22": [
                    "aqYkFCgDRKBLZ4rJ"
                ],
                "2021-10-27": [
                    "zbJPGpZVCYyrhH1T"
                ],
                "2021-11-03": [
                    "vNkLFVZ6mHTPt7G1",
                    "cW62MmnpTJ98bzPL"
                ],
                "2021-11-17": [
                    "qwJgkXp6FyPv8bcx"
                ],
                "2021-11-24": [
                    "jK9WdpQRxD32MP7b"
                ]
            }
        },
        "magtheridon": {
            "percentage": 0.20689655172413793,
            "details": {
                "2021-09-22": [
                    "JdVhRBNmn8a7Cwkq"
                ],
                "2021-10-27": [
                    "zbJPGpZVCYyrhH1T"
                ],
                "2021-11-03": [
                    "cW62MmnpTJ98bzPL"
                ],
                "2021-11-10": [
                    "7RnchN3rf4Zw6Pbm"
                ],
                "2021-11-17": [
                    "qwJgkXp6FyPv8bcx"
                ],
                "2021-11-24": [
                    "jK9WdpQRxD32MP7b"
                ]
            }
        },
        "ssc": {
            "percentage": 0.0,
            "details": {}
        },
        "tk": {
            "percentage": 0.0,
            "details": {}
        }
    },
    "name": "Minela"
}