{
    "raids": [
        {
            "zoneID": 1007,
            "startTime": 1630004423436,
            "reportCode": "DwJ1BxHb6vTtRr7q",
            "bosses": [
                "Attumen the Huntsman",
                "Moroes",
                "Maiden of Virtue",
                "Opera Hall",
                "Nightbane",
                "The Curator",
                "Terestian Illhoof",
                "Shade of Aran - Wipe 1 (9%)",
                "Shade of Aran - Wipe 2 (22%)",
                "Shade of Aran",
                "Netherspite",
                "Prince Malchezaar"
            ]
        },
        {
            "zoneID": 1007,
            "startTime": 1630609674422,
            "reportCode": "mg7WhzNG2dDFp6VQ",
            "bosses": [
                "Attumen the Huntsman",
                "Moroes",
                "Maiden of Virtue",
                "Opera Hall",
                "Nightbane",
                "The Curator",
                "Terestian Illhoof",
                "Shade of Aran - Wipe 1 (5%)",
                "Shade of Aran",
                "Netherspite",
                "Prince Malchezaar"
            ]
        }
    ],
    "attendance": {
        "kharazan": {
            "percentage": 0.11764705882352941,
            "details": {
                "2021-08-25": [
                    "DwJ1BxHb6vTtRr7q"
                ],
                "2021-09-01": [
                    "mg7WhzNG2dDFp6VQ"
                ]
            }
        },
        "gruul": {
            "percentage": 0.0,
            "details": {}
        },
        "magtheridon": {
            "percentage": 0.0,
            "details": {}
        },
        "ssc": {
            "percentage": 0.0,
            "details": {}
        },
        "tk": {
            "percentage": 0.0,
            "details": {}
        }
    },
    "name": "Philippine"
}