{
    "raids": [
        {
            "zoneID": 1008,
            "startTime": 1623178781225,
            "reportCode": "DvRwcyNhqjBfzV8J",
            "bosses": [
                "High King Maulgar",
                "Gruul the Dragonkiller"
            ]
        },
        {
            "zoneID": 1007,
            "startTime": 1623265738231,
            "reportCode": "NFfMkZKQVCayWqr9",
            "bosses": [
                "Attumen the Huntsman",
                "Moroes",
                "Maiden of Virtue",
                "Opera Hall",
                "The Curator",
                "Terestian Illhoof",
                "Shade of Aran",
                "Prince Malchezaar"
            ]
        },
        {
            "zoneID": 1008,
            "startTime": 1623611262101,
            "reportCode": "a63WKht2YpDfkbcx",
            "bosses": [
                "High King Maulgar",
                "Gruul the Dragonkiller"
            ]
        },
        {
            "zoneID": 1008,
            "startTime": 1623697368567,
            "reportCode": "J3hxBZbmfF8G6k1M",
            "bosses": [
                "Magtheridon"
            ]
        },
        {
            "zoneID": 1008,
            "startTime": 1623869884006,
            "reportCode": "bnc4ayLTMCNZgXdJ",
            "bosses": [
                "Magtheridon"
            ]
        },
        {
            "zoneID": 1008,
            "startTime": 1623877533355,
            "reportCode": "ZrA4kgnHCDTzG3Q7",
            "bosses": [
                "High King Maulgar",
                "Gruul the Dragonkiller"
            ]
        },
        {
            "zoneID": 1007,
            "startTime": 1623960459692,
            "reportCode": "vZKMVXPjRrgYh98k",
            "bosses": [
                "Terestian Illhoof",
                "Shade of Aran",
                "Netherspite",
                "Prince Malchezaar",
                "Nightbane"
            ]
        },
        {
            "zoneID": 1007,
            "startTime": 1624475825555,
            "reportCode": "LxB24CWJGadcjRYH",
            "bosses": [
                "Moroes",
                "Maiden of Virtue",
                "Opera Hall",
                "The Curator",
                "Terestian Illhoof",
                "Shade of Aran",
                "Prince Malchezaar",
                "Netherspite",
                "Nightbane"
            ]
        },
        {
            "zoneID": 1007,
            "startTime": 1625165715468,
            "reportCode": "4nCZHq1zGY9M32tT",
            "bosses": [
                "Attumen the Huntsman",
                "Moroes",
                "Maiden of Virtue",
                "Opera Hall",
                "Nightbane",
                "The Curator",
                "Terestian Illhoof",
                "Shade of Aran",
                "Netherspite",
                "Prince Malchezaar"
            ]
        },
        {
            "zoneID": 1008,
            "startTime": 1625427700972,
            "reportCode": "xMb98vDqtyQYJHhp",
            "bosses": [
                "Magtheridon"
            ]
        },
        {
            "zoneID": 1008,
            "startTime": 1625684167277,
            "reportCode": "bjcVfxyKYC18Fqwm",
            "bosses": [
                "High King Maulgar",
                "Gruul the Dragonkiller",
                "Magtheridon"
            ]
        },
        {
            "zoneID": 1007,
            "startTime": 1625770698784,
            "reportCode": "gM3QrbR8wmXyqPBv",
            "bosses": [
                "Attumen the Huntsman",
                "Moroes",
                "Maiden of Virtue",
                "Opera Hall",
                "Nightbane",
                "The Curator",
                "Terestian Illhoof",
                "Shade of Aran",
                "Netherspite",
                "Prince Malchezaar"
            ]
        },
        {
            "zoneID": 1008,
            "startTime": 1626375201415,
            "reportCode": "263vgwqW1G4jMVXT",
            "bosses": [
                "High King Maulgar",
                "Gruul the Dragonkiller",
                "Magtheridon"
            ]
        },
        {
            "zoneID": 1008,
            "startTime": 1626375280199,
            "reportCode": "MQBJarpX1mP8D3Ff",
            "bosses": [
                "High King Maulgar",
                "Gruul the Dragonkiller",
                "Magtheridon"
            ]
        },
        {
            "zoneID": 1008,
            "startTime": 1627239428364,
            "reportCode": "NbHmgz3thQyCjTw8",
            "bosses": [
                "High King Maulgar",
                "Gruul the Dragonkiller",
                "Magtheridon"
            ]
        },
        {
            "zoneID": 1008,
            "startTime": 1627584731853,
            "reportCode": "CZKbdcF3B1xt4Dqh",
            "bosses": [
                "High King Maulgar",
                "Gruul the Dragonkiller",
                "Magtheridon"
            ]
        },
        {
            "zoneID": 1008,
            "startTime": 1627584779061,
            "reportCode": "2Xn4hZpJvRWtL7zC",
            "bosses": [
                "High King Maulgar",
                "Gruul the Dragonkiller",
                "Magtheridon"
            ]
        },
        {
            "zoneID": 1008,
            "startTime": 1628448896837,
            "reportCode": "mY1tCRrf4JbLac3D",
            "bosses": [
                "High King Maulgar",
                "Gruul the Dragonkiller",
                "Magtheridon"
            ]
        },
        {
            "zoneID": 1007,
            "startTime": 1628452370724,
            "reportCode": "wxr1ktL6pZc2f8NW",
            "bosses": [
                "Attumen the Huntsman",
                "Moroes",
                "Maiden of Virtue",
                "Opera Hall",
                "Nightbane",
                "The Curator",
                "Terestian Illhoof",
                "Shade of Aran",
                "Prince Malchezaar",
                "Netherspite"
            ]
        },
        {
            "zoneID": 1008,
            "startTime": 1629054069267,
            "reportCode": "r8MAfh91kWxXTwjv",
            "bosses": [
                "High King Maulgar",
                "Gruul the Dragonkiller",
                "Magtheridon"
            ]
        },
        {
            "zoneID": 1007,
            "startTime": 1629057865361,
            "reportCode": "DcpHaMzy1dkVAw73",
            "bosses": [
                "Attumen the Huntsman",
                "Moroes",
                "Maiden of Virtue",
                "Opera Hall",
                "The Curator",
                "Terestian Illhoof",
                "Shade of Aran",
                "Prince Malchezaar",
                "Netherspite"
            ]
        },
        {
            "zoneID": 1008,
            "startTime": 1629314455557,
            "reportCode": "dQ4yMg7LvVt31Jzx",
            "bosses": [
                "Magtheridon"
            ]
        },
        {
            "zoneID": 1008,
            "startTime": 1629315517497,
            "reportCode": "bTYWj4H3Lx62DMmZ",
            "bosses": [
                "Magtheridon"
            ]
        }
    ],
    "attendance": {
        "kharazan": {
            "percentage": 0.4,
            "details": {
                "2021-06-09": [
                    "NFfMkZKQVCayWqr9"
                ],
                "2021-06-23": [
                    "LxB24CWJGadcjRYH"
                ],
                "2021-06-30": [
                    "4nCZHq1zGY9M32tT"
                ],
                "2021-07-07": [
                    "gM3QrbR8wmXyqPBv"
                ],
                "2021-08-04": [
                    "wxr1ktL6pZc2f8NW"
                ],
                "2021-08-11": [
                    "DcpHaMzy1dkVAw73"
                ]
            }
        },
        "gruul": {
            "percentage": 0.6,
            "details": {
                "2021-06-02": [
                    "DvRwcyNhqjBfzV8J"
                ],
                "2021-06-09": [
                    "a63WKht2YpDfkbcx"
                ],
                "2021-06-16": [
                    "ZrA4kgnHCDTzG3Q7"
                ],
                "2021-07-07": [
                    "bjcVfxyKYC18Fqwm"
                ],
                "2021-07-14": [
                    "263vgwqW1G4jMVXT",
                    "MQBJarpX1mP8D3Ff"
                ],
                "2021-07-21": [
                    "NbHmgz3thQyCjTw8"
                ],
                "2021-07-28": [
                    "CZKbdcF3B1xt4Dqh",
                    "2Xn4hZpJvRWtL7zC"
                ],
                "2021-08-04": [
                    "mY1tCRrf4JbLac3D"
                ],
                "2021-08-11": [
                    "r8MAfh91kWxXTwjv"
                ]
            }
        },
        "magtheridon": {
            "percentage": 0.6666666666666666,
            "details": {
                "2021-06-09": [
                    "J3hxBZbmfF8G6k1M"
                ],
                "2021-06-16": [
                    "bnc4ayLTMCNZgXdJ"
                ],
                "2021-06-30": [
                    "xMb98vDqtyQYJHhp"
                ],
                "2021-07-07": [
                    "bjcVfxyKYC18Fqwm"
                ],
                "2021-07-14": [
                    "263vgwqW1G4jMVXT",
                    "MQBJarpX1mP8D3Ff"
                ],
                "2021-07-21": [
                    "NbHmgz3thQyCjTw8"
                ],
                "2021-07-28": [
                    "CZKbdcF3B1xt4Dqh",
                    "2Xn4hZpJvRWtL7zC"
                ],
                "2021-08-04": [
                    "mY1tCRrf4JbLac3D"
                ],
                "2021-08-11": [
                    "r8MAfh91kWxXTwjv"
                ],
                "2021-08-18": [
                    "dQ4yMg7LvVt31Jzx",
                    "bTYWj4H3Lx62DMmZ"
                ]
            }
        }
    },
    "name": "Z\u00e9npa"
}