{
	"startTime": 1640816691526,
	"endTime": 1640817379972,
	"title": "GRUUL",
	"actors": [
		"Alydara",
		"Andrawe",
		"Aribèth",
		"Aslandy",
		"Avalona",
		"Bibihammer",
		"Bømbas",
		"Deckmír",
		"Demypom",
		"Demø",
		"Fistivalia",
		"Gardyloo",
		"Keva",
		"Lghtningbolt",
		"Lÿnhe",
		"Midge",
		"Misaia",
		"Pissjuana",
		"Row",
		"Sté",
		"Symarina",
		"Söcrate",
		"Torquin",
		"Twinkii",
		"Zvora"
	],
	"zoneID": 1008,
	"fights": {
		"Gruul the Dragonkiller": {
			"startTime": 533041,
			"endTime": 688446,
			"name": "Gruul the Dragonkiller"
		},
		"High King Maulgar": {
			"startTime": 239470,
			"endTime": 349641,
			"name": "High King Maulgar"
		}
	},
	"code": "FGXTQCZL2WJDvhrb"
}
