{
     "startTime": 1635360054725,
     "endTime": 1635373087329,
     "title": "SR",
     "actors": [
         "Abumi",
         "Amdal",
         "Andrawe",
         "Ankw",
         "Aslandy",
         "Avalona",
         "Bladorthin",
         "Bømbas",
         "Bøømba",
         "Deckmír",
         "Demypom",
         "Grwah",
         "Krijae",
         "Lablatte",
         "Limpo",
         "Lÿnhe",
         "Matroth",
         "Misaia",
         "Pititbibi",
         "Sikohex",
         "Sté",
         "Weg",
         "Zail",
         "Zvora",
         "Öwned"
     ],
     "zoneID": 1010,
     "fights": {
         "Al'ar": {
             "startTime": 941628,
             "endTime": 1288677,
             "name": "Al'ar"
         },
         "Fathom-Lord Karathress": {
             "startTime": 10773167,
             "endTime": 10979365,
             "name": "Fathom-Lord Karathress"
         },
         "High Astromancer Solarian": {
             "startTime": 3158918,
             "endTime": 3381114,
             "name": "High Astromancer Solarian"
         },
         "Hydross the Unstable": {
             "startTime": 7435643,
             "endTime": 7612790,
             "name": "Hydross the Unstable"
         },
         "Kael'thas Sunstrider": {
             "startTime": 5847421,
             "endTime": 6523373,
             "name": "Kael'thas Sunstrider"
         },
         "Lady Vashj": {
             "startTime": 12417791,
             "endTime": 12932122,
             "name": "Lady Vashj"
         },
         "Leotheras the Blind": {
             "startTime": 11671916,
             "endTime": 12041042,
             "name": "Leotheras the Blind"
         },
         "Morogrim Tidewalker": {
             "startTime": 9669078,
             "endTime": 9936414,
             "name": "Morogrim Tidewalker"
         },
         "The Lurker Below": {
             "startTime": 8260645,
             "endTime": 8567482,
             "name": "The Lurker Below"
         },
         "Void Reaver": {
             "startTime": 2164679,
             "endTime": 2335773,
             "name": "Void Reaver"
         }
     },
     "code": "rVpzvcA41aDZnCdJ"
 }
