{
    "startTime": 1631473201504,
    "title": "Origin - Gruul/Magtherion - 12/096/2021 - Raid 2",
    "actors": [
        "Lentulus",
        "Abumi",
        "Pititbibi",
        "Row",
        "Billes",
        "Krija",
        "Andrawe",
        "Bodalen",
        "Mabey",
        "Misaia",
        "Symarina",
        "Stifmeister",
        "B\u00f8mbas",
        "Demypom",
        "Twinkii",
        "Weg",
        "Windfurypls",
        "Torinoo",
        "Gardyloo",
        "Doodo",
        "Keva",
        "Airod",
        "Zvora",
        "N\u00e4ely",
        "Zailol",
        "Farf\u00e4"
    ],
    "zoneID": 1008,
    "fights": {
        "High King Maulgar": {
            "startTime": 242640,
            "endTime": 415467
        },
        "Gruul the Dragonkiller": {
            "startTime": 785449,
            "endTime": 1128556
        },
        "Magtheridon": {
            "startTime": 3200508,
            "endTime": 3648174
        }
    }
}