{
    "startTime": 1625080035398,
    "title": "Origin - Karazhan - 30/06/2021 - Groupe Boomba",
    "actors": [
        "Raca",
        "Fabr\u00efste",
        "Touinki",
        "S\u00f6crate",
        "B\u00f8\u00f8mba",
        "Ayurvedae",
        "Zvora",
        "Krijae",
        "Lablatte",
        "Weg"
    ],
    "zoneID": 1007,
    "fights": {
        "Attumen the Huntsman": {
            "startTime": 622752,
            "endTime": 788321,
            "name": "Attumen the Huntsman"
        },
        "Moroes": {
            "startTime": 1805967,
            "endTime": 1943929,
            "name": "Moroes"
        },
        "Maiden of Virtue": {
            "startTime": 2830452,
            "endTime": 2932679,
            "name": "Maiden of Virtue"
        },
        "Opera Hall": {
            "startTime": 3705003,
            "endTime": 3868608,
            "name": "Opera Hall"
        },
        "The Curator": {
            "startTime": 5100311,
            "endTime": 5232581,
            "name": "The Curator"
        },
        "Terestian Illhoof": {
            "startTime": 6240790,
            "endTime": 6381291,
            "name": "Terestian Illhoof"
        },
        "Shade of Aran": {
            "startTime": 6734221,
            "endTime": 6946070,
            "name": "Shade of Aran"
        },
        "Netherspite - Wipe 1 (46%)": {
            "startTime": 8011410,
            "endTime": 8226999,
            "name": "Netherspite - Wipe 1 (46%)"
        },
        "Netherspite - Wipe 2 (100%)": {
            "startTime": 8556435,
            "endTime": 8711613,
            "name": "Netherspite - Wipe 2 (100%)"
        },
        "Chess Event": {
            "startTime": 9028783,
            "endTime": 9174665,
            "name": "Chess Event"
        },
        "Prince Malchezaar - Wipe 1 (49%)": {
            "startTime": 9622738,
            "endTime": 9740842,
            "name": "Prince Malchezaar - Wipe 1 (49%)"
        },
        "Prince Malchezaar": {
            "startTime": 10050634,
            "endTime": 10274436,
            "name": "Prince Malchezaar"
        },
        "Netherspite": {
            "startTime": 10744847,
            "endTime": 10933283,
            "name": "Netherspite"
        }
    },
    "code": "nyaC3G4b2hVFZTMN"
}