{
    "startTime": 1634151593549,
    "title": "Origin - SSC - 13/10/21",
    "actors": [
        "Sikohex",
        "Pissjuana",
        "Torquin",
        "Zail",
        "Lght",
        "Lablatte",
        "Izyheal",
        "L\u00ffnhe",
        "Demypom",
        "B\u00e3bynou",
        "Bladorthin",
        "Weg",
        "Windfurypls",
        "Fabr\u00efste",
        "Touinki",
        "Aslandy",
        "Deckm\u00edr",
        "Darcia",
        "Grwah",
        "Kyore",
        "Ankw",
        "\u00d6wned",
        "Airod",
        "Avalona",
        "Mfarfadet"
    ],
    "zoneID": 1010,
    "fights": {
        "Hydross the Unstable": {
            "startTime": 414705,
            "endTime": 593173,
            "name": "Hydross the Unstable"
        },
        "The Lurker Below": {
            "startTime": 1339635,
            "endTime": 1698644,
            "name": "The Lurker Below"
        },
        "Morogrim Tidewalker - Wipe 1 (56%)": {
            "startTime": 3115934,
            "endTime": 3278779,
            "name": "Morogrim Tidewalker - Wipe 1 (56%)"
        },
        "Morogrim Tidewalker": {
            "startTime": 3528636,
            "endTime": 3792673,
            "name": "Morogrim Tidewalker"
        },
        "Fathom-Lord Karathress": {
            "startTime": 4540542,
            "endTime": 4759841,
            "name": "Fathom-Lord Karathress"
        },
        "Leotheras the Blind": {
            "startTime": 5552481,
            "endTime": 5825486,
            "name": "Leotheras the Blind"
        },
        "Lady Vashj": {
            "startTime": 6249773,
            "endTime": 6779954,
            "name": "Lady Vashj"
        }
    },
    "code": "myFRA4TGrc1awWMk"
}