{
    "startTime": 1635360278310,
    "title": "TK Bis",
    "actors": [
        "Sikohex",
        "Abumi",
        "Pititbibi",
        "Zail",
        "Limpo",
        "Andrawe",
        "Krijae",
        "Lablatte",
        "Misaia",
        "St\u00e9",
        "B\u00f8\u00f8mba",
        "L\u00ffnhe",
        "B\u00f8mbas",
        "Demypom",
        "Amdal",
        "Bladorthin",
        "Weg",
        "Matroth",
        "Aslandy",
        "Deckm\u00edr",
        "Grwah",
        "Ankw",
        "\u00d6wned",
        "Zvora",
        "Avalona"
    ],
    "zoneID": 1010,
    "fights": {
        "Al'ar": {
            "startTime": 716641,
            "endTime": 1063682,
            "name": "Al'ar"
        },
        "Void Reaver": {
            "startTime": 1939701,
            "endTime": 2110792,
            "name": "Void Reaver"
        },
        "High Astromancer Solarian": {
            "startTime": 2933938,
            "endTime": 3156135,
            "name": "High Astromancer Solarian"
        },
        "Kael'thas Sunstrider": {
            "startTime": 5622431,
            "endTime": 6298427,
            "name": "Kael'thas Sunstrider"
        }
    },
    "code": "Bb7CFY8H2wvRK6yZ"
}