{
     "startTime": 1630868393829,
     "endTime": 1630870629528,
     "title": "Origin - Gruul/Magtheridon - 05/09/2021 - Raid 2",
     "actors": [
         "Abumi",
         "Airod",
         "Andrawe",
         "Ankw",
         "Aslandy",
         "Bodalen",
         "Bømbas",
         "Bøømba",
         "Clownyx",
         "Darcia",
         "Dwalïn",
         "Fabrïste",
         "Heùtch",
         "Lablatte",
         "Lentulus",
         "Mebrykikoo",
         "Mfarfadet",
         "Nekonome",
         "Row",
         "Symarina",
         "Torinoo",
         "Touinki",
         "Weg",
         "Zail",
         "Zvorà"
     ],
     "zoneID": 1008,
     "fights": {
         "Gruul the Dragonkiller": {
             "startTime": 713300,
             "endTime": 999978,
             "name": "Gruul the Dragonkiller"
         },
         "High King Maulgar": {
             "startTime": 242226,
             "endTime": 383987,
             "name": "High King Maulgar"
         },
         "Magtheridon": {
             "startTime": 1817648,
             "endTime": 2235699,
             "name": "Magtheridon"
         }
     },
     "code": "MxZpXvtfTznDJB4h"
 }
