{
    "startTime": 1631214940771,
    "title": "Karazhan",
    "actors": [
        "Minela",
        "Zail",
        "Symarina",
        "Farf\u00e4",
        "Andrawe",
        "Zvor\u00e0",
        "B\u00f8\u00f8mbit\u00e4",
        "Torquine",
        "Weg",
        "Windfurypls"
    ],
    "zoneID": 1007,
    "fights": {
        "Attumen the Huntsman": {
            "startTime": 463512,
            "endTime": 583711
        },
        "Moroes": {
            "startTime": 918825,
            "endTime": 1056712
        },
        "Maiden of Virtue": {
            "startTime": 1568018,
            "endTime": 1657636
        },
        "Opera Hall": {
            "startTime": 2188863,
            "endTime": 2258118
        },
        "Nightbane": {
            "startTime": 3909897,
            "endTime": 4312462
        },
        "The Curator": {
            "startTime": 4818540,
            "endTime": 4958599
        },
        "Terestian Illhoof": {
            "startTime": 5731148,
            "endTime": 5882071
        },
        "Shade of Aran": {
            "startTime": 6108812,
            "endTime": 6295882
        },
        "Netherspite": {
            "startTime": 7000503,
            "endTime": 7186339
        },
        "Chess Event": {
            "startTime": 7452816,
            "endTime": 7546916
        },
        "Prince Malchezaar": {
            "startTime": 7836163,
            "endTime": 8053711
        }
    }
}