{
    "startTime": 1636322217107,
    "title": "TK #2",
    "actors": [
        "Lentulus",
        "Abumi",
        "Pititbibi",
        "Row",
        "A\u00eblendr\u00efll",
        "Zail",
        "Lghtningbolt",
        "Krijae",
        "Arib\u00e8th",
        "Muflax",
        "Izyheal",
        "Symarina",
        "St\u00e9",
        "L\u00ffnhe",
        "Bladorthin",
        "Sikolette",
        "B\u00e3bynou",
        "Matroth",
        "Aslandy",
        "Darcia",
        "Grwah",
        "Kyore",
        "\u00d6wned",
        "Avalona",
        "Mfarfadet"
    ],
    "zoneID": 1010,
    "fights": {
        "Al'ar": {
            "startTime": 837469,
            "endTime": 1231388,
            "name": "Al'ar"
        },
        "Void Reaver": {
            "startTime": 2232502,
            "endTime": 2398283,
            "name": "Void Reaver"
        },
        "High Astromancer Solarian": {
            "startTime": 3338186,
            "endTime": 3575568,
            "name": "High Astromancer Solarian"
        }
    },
    "code": "waGTD9Y1X3fCc7Lm"
}