{
    "code": "pcFj9nPaXkhA2mvg",
    "endTime": 1625169953282,
    "startTime": 1625168526507,
    "title": "Nightbane Boomba",
    "zone": {
        "id": 1007
    },
    "masterData": {
        "lang": "fr",
        "abilities": [
            {
                "gameID": 0,
                "type": "0"
            },
            {
                "gameID": 43308,
                "type": "1"
            },
            {
                "gameID": 28143,
                "type": "64"
            },
            {
                "gameID": 26990,
                "type": "8"
            },
            {
                "gameID": 5502,
                "type": "2"
            },
            {
                "gameID": 32223,
                "type": "2"
            },
            {
                "gameID": 25898,
                "type": "2"
            },
            {
                "gameID": 19880,
                "type": "1"
            },
            {
                "gameID": 27044,
                "type": "8"
            },
            {
                "gameID": 27141,
                "type": "2"
            },
            {
                "gameID": 27268,
                "type": "32"
            },
            {
                "gameID": 4511,
                "type": "1"
            },
            {
                "gameID": 28189,
                "type": "32"
            },
            {
                "gameID": 27127,
                "type": "64"
            },
            {
                "gameID": 33081,
                "type": "8"
            },
            {
                "gameID": 26991,
                "type": "8"
            },
            {
                "gameID": 17539,
                "type": "1"
            },
            {
                "gameID": 27149,
                "type": "2"
            },
            {
                "gameID": 30482,
                "type": "4"
            },
            {
                "gameID": 27126,
                "type": "64"
            },
            {
                "gameID": 2383,
                "type": "1"
            },
            {
                "gameID": 1953,
                "type": "64"
            },
            {
                "gameID": 18708,
                "type": "32"
            },
            {
                "gameID": 712,
                "type": "32"
            },
            {
                "gameID": 32752,
                "type": "1"
            },
            {
                "gameID": 18791,
                "type": "32"
            },
            {
                "gameID": 18788,
                "type": "32"
            },
            {
                "gameID": 27145,
                "type": "2"
            },
            {
                "gameID": 43987,
                "type": "64"
            },
            {
                "gameID": 25780,
                "type": "2"
            },
            {
                "gameID": 29893,
                "type": "32"
            },
            {
                "gameID": 27143,
                "type": "2"
            },
            {
                "gameID": 16864,
                "type": "8"
            },
            {
                "gameID": 33254,
                "type": "1"
            },
            {
                "gameID": 17116,
                "type": "1"
            },
            {
                "gameID": 8143,
                "type": "8"
            },
            {
                "gameID": 26891,
                "type": "1"
            },
            {
                "gameID": 27186,
                "type": "1"
            },
            {
                "gameID": 26992,
                "type": "8"
            },
            {
                "gameID": 33763,
                "type": "8"
            },
            {
                "gameID": 33370,
                "type": "1"
            },
            {
                "gameID": 34585,
                "type": "1"
            },
            {
                "gameID": 31786,
                "type": "1"
            },
            {
                "gameID": 20216,
                "type": "2"
            },
            {
                "gameID": 33778,
                "type": "8"
            },
            {
                "gameID": 768,
                "type": "1"
            },
            {
                "gameID": 24932,
                "type": "1"
            },
            {
                "gameID": 5225,
                "type": "1"
            },
            {
                "gameID": 17099,
                "type": "1"
            },
            {
                "gameID": 28491,
                "type": "1"
            },
            {
                "gameID": 39627,
                "type": "1"
            },
            {
                "gameID": 33265,
                "type": "1"
            },
            {
                "gameID": 25123,
                "type": "1"
            },
            {
                "gameID": 27137,
                "type": "2"
            },
            {
                "gameID": 27136,
                "type": "2"
            },
            {
                "gameID": 33721,
                "type": "1"
            },
            {
                "gameID": 32594,
                "type": "8"
            },
            {
                "gameID": 28017,
                "type": "1"
            },
            {
                "gameID": 33736,
                "type": "8"
            },
            {
                "gameID": 33263,
                "type": "1"
            },
            {
                "gameID": 25895,
                "type": "2"
            },
            {
                "gameID": 1038,
                "type": "2"
            },
            {
                "gameID": 27169,
                "type": "2"
            },
            {
                "gameID": 27142,
                "type": "2"
            },
            {
                "gameID": 25122,
                "type": "1"
            },
            {
                "gameID": 11474,
                "type": "4"
            },
            {
                "gameID": 33261,
                "type": "1"
            },
            {
                "gameID": 16595,
                "type": "1"
            },
            {
                "gameID": 16589,
                "type": "1"
            },
            {
                "gameID": 16593,
                "type": "1"
            },
            {
                "gameID": 33891,
                "type": "1"
            },
            {
                "gameID": 34123,
                "type": "1"
            },
            {
                "gameID": 28497,
                "type": "1"
            },
            {
                "gameID": 11348,
                "type": "1"
            },
            {
                "gameID": 43764,
                "type": "1"
            },
            {
                "gameID": 16591,
                "type": "1"
            },
            {
                "gameID": 1787,
                "type": "1"
            },
            {
                "gameID": 9913,
                "type": "1"
            },
            {
                "gameID": 25567,
                "type": "16"
            },
            {
                "gameID": 3738,
                "type": "1"
            },
            {
                "gameID": 25566,
                "type": "8"
            },
            {
                "gameID": 27155,
                "type": "2"
            },
            {
                "gameID": 27179,
                "type": "2"
            },
            {
                "gameID": 27173,
                "type": "2"
            },
            {
                "gameID": 1,
                "type": "1"
            },
            {
                "gameID": 30130,
                "type": "4"
            },
            {
                "gameID": 27138,
                "type": "2"
            },
            {
                "gameID": 20271,
                "type": "2"
            },
            {
                "gameID": 27157,
                "type": "2"
            },
            {
                "gameID": 27228,
                "type": "32"
            },
            {
                "gameID": 31801,
                "type": "2"
            },
            {
                "gameID": 4987,
                "type": "2"
            },
            {
                "gameID": 27074,
                "type": "4"
            },
            {
                "gameID": 23110,
                "type": "1"
            },
            {
                "gameID": 27216,
                "type": "32"
            },
            {
                "gameID": 32391,
                "type": "32"
            },
            {
                "gameID": 331,
                "type": "8"
            },
            {
                "gameID": 22959,
                "type": "4"
            },
            {
                "gameID": 34120,
                "type": "1"
            },
            {
                "gameID": 29203,
                "type": "8"
            },
            {
                "gameID": 30405,
                "type": "32"
            },
            {
                "gameID": 75,
                "type": "1"
            },
            {
                "gameID": 26980,
                "type": "8"
            },
            {
                "gameID": 35298,
                "type": "1"
            },
            {
                "gameID": 27005,
                "type": "1"
            },
            {
                "gameID": 34299,
                "type": "1"
            },
            {
                "gameID": 31803,
                "type": "2"
            },
            {
                "gameID": 16459,
                "type": "1"
            },
            {
                "gameID": 26862,
                "type": "1"
            },
            {
                "gameID": 379,
                "type": "8"
            },
            {
                "gameID": 26982,
                "type": "8"
            },
            {
                "gameID": 27050,
                "type": "1"
            },
            {
                "gameID": 27002,
                "type": "1"
            },
            {
                "gameID": 6774,
                "type": "1"
            },
            {
                "gameID": 6150,
                "type": "1"
            },
            {
                "gameID": 34471,
                "type": "1"
            },
            {
                "gameID": 19574,
                "type": "1"
            },
            {
                "gameID": 35166,
                "type": "1"
            },
            {
                "gameID": 27209,
                "type": "32"
            },
            {
                "gameID": 34953,
                "type": "1"
            },
            {
                "gameID": 3045,
                "type": "64"
            },
            {
                "gameID": 25396,
                "type": "8"
            },
            {
                "gameID": 30911,
                "type": "32"
            },
            {
                "gameID": 13750,
                "type": "1"
            },
            {
                "gameID": 34026,
                "type": "1"
            },
            {
                "gameID": 34027,
                "type": "1"
            },
            {
                "gameID": 19615,
                "type": "1"
            },
            {
                "gameID": 34456,
                "type": "1"
            },
            {
                "gameID": 28866,
                "type": "1"
            },
            {
                "gameID": 20272,
                "type": "1"
            },
            {
                "gameID": 27011,
                "type": "8"
            },
            {
                "gameID": 27166,
                "type": "2"
            },
            {
                "gameID": 27164,
                "type": "2"
            },
            {
                "gameID": 27267,
                "type": "4"
            },
            {
                "gameID": 27165,
                "type": "2"
            },
            {
                "gameID": 27187,
                "type": "8"
            },
            {
                "gameID": 12654,
                "type": "4"
            },
            {
                "gameID": 29077,
                "type": "64"
            },
            {
                "gameID": 27070,
                "type": "4"
            },
            {
                "gameID": 25423,
                "type": "8"
            },
            {
                "gameID": 13877,
                "type": "1"
            },
            {
                "gameID": 17800,
                "type": "32"
            },
            {
                "gameID": 20007,
                "type": "1"
            },
            {
                "gameID": 1064,
                "type": "8"
            },
            {
                "gameID": 30909,
                "type": "32"
            },
            {
                "gameID": 35548,
                "type": "1"
            },
            {
                "gameID": 26867,
                "type": "1"
            },
            {
                "gameID": 14181,
                "type": "1"
            },
            {
                "gameID": 27008,
                "type": "1"
            },
            {
                "gameID": 28722,
                "type": "64"
            },
            {
                "gameID": 27215,
                "type": "4"
            },
            {
                "gameID": 30209,
                "type": "1"
            },
            {
                "gameID": 30129,
                "type": "1"
            },
            {
                "gameID": 30131,
                "type": "1"
            },
            {
                "gameID": 31804,
                "type": "2"
            },
            {
                "gameID": 25653,
                "type": "4"
            },
            {
                "gameID": 16870,
                "type": "8"
            },
            {
                "gameID": 33983,
                "type": "1"
            },
            {
                "gameID": 28839,
                "type": "1"
            },
            {
                "gameID": 35337,
                "type": "64"
            },
            {
                "gameID": 27222,
                "type": "32"
            },
            {
                "gameID": 31818,
                "type": "32"
            },
            {
                "gameID": 42463,
                "type": "2"
            },
            {
                "gameID": 27223,
                "type": "32"
            },
            {
                "gameID": 32108,
                "type": "64"
            },
            {
                "gameID": 30210,
                "type": "4"
            },
            {
                "gameID": 17941,
                "type": "32"
            },
            {
                "gameID": 18562,
                "type": "8"
            },
            {
                "gameID": 16237,
                "type": "2"
            },
            {
                "gameID": 31834,
                "type": "2"
            },
            {
                "gameID": 33737,
                "type": "8"
            },
            {
                "gameID": 28499,
                "type": "1"
            },
            {
                "gameID": 27003,
                "type": "1"
            },
            {
                "gameID": 27218,
                "type": "32"
            },
            {
                "gameID": 27103,
                "type": "1"
            },
            {
                "gameID": 13809,
                "type": "16"
            },
            {
                "gameID": 31842,
                "type": "2"
            },
            {
                "gameID": 37098,
                "type": "1"
            },
            {
                "gameID": 37091,
                "type": "1"
            },
            {
                "gameID": 37059,
                "type": "4"
            },
            {
                "gameID": 27088,
                "type": "16"
            },
            {
                "gameID": 27156,
                "type": "2"
            },
            {
                "gameID": 27243,
                "type": "32"
            },
            {
                "gameID": 37060,
                "type": "4"
            },
            {
                "gameID": 35165,
                "type": "1"
            },
            {
                "gameID": 33072,
                "type": "2"
            },
            {
                "gameID": 33074,
                "type": "2"
            },
            {
                "gameID": 27086,
                "type": "4"
            },
            {
                "gameID": 22812,
                "type": "8"
            },
            {
                "gameID": 13810,
                "type": "16"
            },
            {
                "gameID": 10308,
                "type": "2"
            },
            {
                "gameID": 2764,
                "type": "1"
            },
            {
                "gameID": 27285,
                "type": "32"
            },
            {
                "gameID": 27085,
                "type": "16"
            },
            {
                "gameID": 27021,
                "type": "1"
            },
            {
                "gameID": 42198,
                "type": "16"
            },
            {
                "gameID": 30128,
                "type": "1"
            },
            {
                "gameID": 30127,
                "type": "4"
            },
            {
                "gameID": 25420,
                "type": "8"
            },
            {
                "gameID": 31789,
                "type": "2"
            },
            {
                "gameID": 31790,
                "type": "1"
            },
            {
                "gameID": 37057,
                "type": "1"
            },
            {
                "gameID": 37379,
                "type": "1"
            },
            {
                "gameID": 32700,
                "type": "2"
            },
            {
                "gameID": 34477,
                "type": "1"
            },
            {
                "gameID": 35079,
                "type": "1"
            },
            {
                "gameID": 28779,
                "type": "1"
            },
            {
                "gameID": 14325,
                "type": "64"
            },
            {
                "gameID": 30912,
                "type": "4"
            },
            {
                "gameID": 34000,
                "type": "64"
            },
            {
                "gameID": 5940,
                "type": "1"
            },
            {
                "gameID": 10396,
                "type": "8"
            },
            {
                "gameID": 30546,
                "type": "32"
            },
            {
                "gameID": 29341,
                "type": "32"
            },
            {
                "gameID": 34074,
                "type": "8"
            },
            {
                "gameID": 12051,
                "type": "64"
            },
            {
                "gameID": 31224,
                "type": "1"
            },
            {
                "gameID": 27031,
                "type": "1"
            },
            {
                "gameID": 11196,
                "type": "1"
            },
            {
                "gameID": 27237,
                "type": "1"
            },
            {
                "gameID": 34936,
                "type": "4"
            },
            {
                "gameID": 27180,
                "type": "2"
            },
            {
                "gameID": 33933,
                "type": "4"
            },
            {
                "gameID": 35099,
                "type": "1"
            },
            {
                "gameID": 27046,
                "type": "8"
            },
            {
                "gameID": 29166,
                "type": "8"
            },
            {
                "gameID": 28724,
                "type": "64"
            },
            {
                "gameID": 16190,
                "type": "16"
            },
            {
                "gameID": 39609,
                "type": "32"
            },
            {
                "gameID": 27079,
                "type": "4"
            },
            {
                "gameID": 20357,
                "type": "2"
            },
            {
                "gameID": 20355,
                "type": "2"
            },
            {
                "gameID": 20353,
                "type": "2"
            },
            {
                "gameID": 17530,
                "type": "1"
            },
            {
                "gameID": 35476,
                "type": "1"
            },
            {
                "gameID": 51120,
                "type": "1"
            },
            {
                "gameID": 32182,
                "type": "8"
            },
            {
                "gameID": 11305,
                "type": "1"
            },
            {
                "gameID": 1604,
                "type": "1"
            },
            {
                "gameID": 28495,
                "type": "1"
            },
            {
                "gameID": 31616,
                "type": "8"
            },
            {
                "gameID": 26890,
                "type": "8"
            },
            {
                "gameID": 28515,
                "type": "1"
            },
            {
                "gameID": 28682,
                "type": "4"
            },
            {
                "gameID": 12472,
                "type": "16"
            },
            {
                "gameID": 23723,
                "type": "64"
            },
            {
                "gameID": 38332,
                "type": "1"
            },
            {
                "gameID": 38333,
                "type": "8"
            },
            {
                "gameID": 25449,
                "type": "8"
            },
            {
                "gameID": 26865,
                "type": "1"
            },
            {
                "gameID": 41425,
                "type": "16"
            },
            {
                "gameID": 45438,
                "type": "16"
            },
            {
                "gameID": 33357,
                "type": "1"
            },
            {
                "gameID": 27235,
                "type": "1"
            },
            {
                "gameID": 1020,
                "type": "2"
            },
            {
                "gameID": 25771,
                "type": "2"
            },
            {
                "gameID": 5019,
                "type": "1"
            },
            {
                "gameID": 34913,
                "type": "4"
            },
            {
                "gameID": 20773,
                "type": "2"
            },
            {
                "gameID": 688,
                "type": "32"
            },
            {
                "gameID": 982,
                "type": "8"
            },
            {
                "gameID": 8690,
                "type": "1"
            },
            {
                "gameID": 3,
                "type": "1"
            },
            {
                "gameID": 6991,
                "type": "1"
            },
            {
                "gameID": 1539,
                "type": "1"
            },
            {
                "gameID": 27131,
                "type": "64"
            }
        ],
        "actors": [
            {
                "gameID": 0,
                "name": "Environment",
                "petOwner": null,
                "type": "NPC",
                "subType": "NPC"
            },
            {
                "gameID": 17213851,
                "name": "Krijae",
                "petOwner": null,
                "type": "Player",
                "subType": "Warlock"
            },
            {
                "gameID": 14937837,
                "name": "Nyand\u00f8",
                "petOwner": null,
                "type": "Player",
                "subType": "Unknown"
            },
            {
                "gameID": 12617454,
                "name": "Weg",
                "petOwner": null,
                "type": "Player",
                "subType": "Paladin"
            },
            {
                "gameID": 15722735,
                "name": "Raca",
                "petOwner": null,
                "type": "Player",
                "subType": "Paladin"
            },
            {
                "gameID": 22246773,
                "name": "B\u00f8\u00f8mba",
                "petOwner": null,
                "type": "Player",
                "subType": "Hunter"
            },
            {
                "gameID": 2745886,
                "name": "Aznar",
                "petOwner": 7,
                "type": "Pet",
                "subType": "Pet"
            },
            {
                "gameID": 26340239,
                "name": "Lablatte",
                "petOwner": null,
                "type": "Player",
                "subType": "Warlock"
            },
            {
                "gameID": 26977935,
                "name": "S\u00f6crate",
                "petOwner": null,
                "type": "Player",
                "subType": "Mage"
            },
            {
                "gameID": 27467288,
                "name": "Zvora",
                "petOwner": null,
                "type": "Player",
                "subType": "Druid"
            },
            {
                "gameID": 17266741,
                "name": "Touinki",
                "petOwner": null,
                "type": "Player",
                "subType": "Rogue"
            },
            {
                "gameID": 940400,
                "name": "Hathgore",
                "petOwner": null,
                "type": "Pet",
                "subType": "Pet"
            },
            {
                "gameID": 4538052,
                "name": "Amdoul",
                "petOwner": 5,
                "type": "Pet",
                "subType": "Pet"
            },
            {
                "gameID": 1099390,
                "name": "Cattora",
                "petOwner": 1,
                "type": "Pet",
                "subType": "Pet"
            },
            {
                "gameID": 186811,
                "name": "Portail \u00e0 rafra\u00eechissements",
                "petOwner": 8,
                "type": "Pet",
                "subType": "Pet"
            },
            {
                "gameID": 181622,
                "name": "Portail des \u00e2mes",
                "petOwner": 1,
                "type": "Pet",
                "subType": "Pet"
            },
            {
                "gameID": 38806377,
                "name": "Ayurvedae",
                "petOwner": null,
                "type": "Player",
                "subType": "Shaman"
            },
            {
                "gameID": 181622,
                "name": "Portail des \u00e2mes",
                "petOwner": 7,
                "type": "Pet",
                "subType": "Pet"
            },
            {
                "gameID": 34467580,
                "name": "Fabr\u00efste",
                "petOwner": null,
                "type": "Player",
                "subType": "Druid"
            },
            {
                "gameID": 20827672,
                "name": "T\u00e2te",
                "petOwner": null,
                "type": "Player",
                "subType": "Unknown"
            },
            {
                "gameID": 5913,
                "name": "Tremor Totem",
                "petOwner": 16,
                "type": "Pet",
                "subType": "Pet"
            },
            {
                "gameID": 15488,
                "name": "zzOLDHealing Stream Totem VI",
                "petOwner": 16,
                "type": "Pet",
                "subType": "Pet"
            },
            {
                "gameID": 15447,
                "name": "Wrath of Air Totem",
                "petOwner": 16,
                "type": "Pet",
                "subType": "Pet"
            },
            {
                "gameID": 17225,
                "name": "Nightbane",
                "petOwner": null,
                "type": "NPC",
                "subType": "Boss"
            },
            {
                "gameID": 164639,
                "name": "Pi\u00e8ge de givre",
                "petOwner": 5,
                "type": "Pet",
                "subType": "Pet"
            },
            {
                "gameID": 17261,
                "name": "Restless Skeleton",
                "petOwner": null,
                "type": "NPC",
                "subType": "NPC"
            },
            {
                "gameID": 17261,
                "name": "Restless Skeleton",
                "petOwner": null,
                "type": "NPC",
                "subType": "NPC"
            },
            {
                "gameID": 10467,
                "name": "Mana Tide Totem",
                "petOwner": 16,
                "type": "Pet",
                "subType": "Pet"
            }
        ]
    },
    "fights": [
        {
            "encounterID": 662,
            "startTime": 428973,
            "endTime": 846581,
            "name": "Nightbane",
            "enemyNPCs": [
                {
                    "gameID": 17225,
                    "id": 23,
                    "instanceCount": 1,
                    "groupCount": 1
                },
                {
                    "gameID": 17261,
                    "id": 26,
                    "instanceCount": 15,
                    "groupCount": 3
                }
            ],
            "friendlyPlayers": [
                4,
                18,
                10,
                8,
                5,
                16,
                9,
                1,
                3,
                7
            ],
            "events": []
        }
    ]
}